diffql/.DS_Store
diffql/__init__.py
diffql/agents/__init__.py
diffql/agents/agents.py
diffql/agents/lqr.py
diffql/agents/pcq_agent.py
diffql/agents/random.py
diffql/config/agents/lse.yml
diffql/config/agents/lse_no_penalty.yml
diffql/config/agents/lse_relu.yml
diffql/config/agents/optimal.yml
diffql/config/agents/plse.yml
diffql/config/agents/plse_no_penalty.yml
diffql/config/agents/plse_relu.yml
diffql/config/agents/quadratic.yml
diffql/config/agents/random.yml
diffql/config/default.yml
diffql/config/envs/CCVFighter.yml
diffql/config/envs/F16LongLinear.yml
diffql/config/envs/F16LongLinear3Dim.yml
diffql/config/envs/Mechanical.yml
diffql/config/envs/Simple.yml
diffql/config/envs/TwoDimDT.yml
diffql/envs/__init__.py
diffql/envs/basic.py
diffql/envs/envs.py
diffql/envs/fixed_wing.py
diffql/learning.py
diffql/networks.py
diffql/sim.py
diffql/utils.py
diffql-0.2.1.dist-info/LICENSE
diffql-0.2.1.dist-info/WHEEL
diffql-0.2.1.dist-info/METADATA
diffql-0.2.1.dist-info/RECORD
