Metadata-Version: 2.1
Name: diffql
Version: 0.2.1
Summary: Differentiable Q-learning (DiffQL) for continuous-action deep reinforcement learning
License: MIT
Author: Jinrae Kim
Author-email: kjl950403@gmail.com
Requires-Python: >=3.9,<3.10
Classifier: License :: OSI Approved :: MIT License
Classifier: Programming Language :: Python :: 3
Classifier: Programming Language :: Python :: 3.9
Requires-Dist: Mosek (>=9.3,<9.4)
Requires-Dist: PyYAML (>=6.0,<6.1)
Requires-Dist: cvxpy (>=1.2,<1.3)
Requires-Dist: cvxpylayers (>=0.1,<0.2)
Requires-Dist: gym (>=0.22,<0.23)
Requires-Dist: numpy (>=1.22,<1.23)
Requires-Dist: scipy (>=1.8,<1.9)
Requires-Dist: torch (>=1.11,<1.12)
Requires-Dist: wandb (>=0.12,<0.13)
